{
  "algo_parameters": {
    "name": "PPO2",
    "seed": 5031998,
    "torch_deterministic": true,
    "cuda": false,
    "track": true,
    "total_timesteps": 500000,
    "learning_rate": 1e-2,
    "num_envs": 10,
    "num_steps": 128,
    "reset_steps": 128,
    "anneal_lr": true,
    "gamma": 0.5,
    "gae_lambda": 0.95,
    "num_minibatches": 4,
    "update_epochs": 10,
    "norm_adv": true,
    "clip_coef": 0.2,
    "clip_vloss": false,
    "ent_coef": 0.0,
    "vf_coef": 0.5,
    "max_grad_norm": 0.5,
    "target_kl": "None",
    "no_improv_thresh": 10
  }
}